Workbook
Name CajaAntes: RESULTADO!$B$5:$G$22
Name CajaDespues: RESULTADO!$I$5:$N$22
Name CajaOriginal: PROYECTO!$E$5:$J$20
Name CfgCarpeta: AJUSTES!$C$9
Name CfgModeloGemini: AJUSTES!$C$7
Name CfgModeloOpenAI: AJUSTES!$C$8
Name CfgMotor: AJUSTES!$C$6
Name CodCalidadOpenAI: CALC!$B$21
Name CodProporcion: CALC!$B$18
Name CodResolucion: CALC!$B$20
Name EstadoApp: PROYECTO!$C$39
Name EstadoClaveGemini: AJUSTES!$C$12
Name EstadoClaveOpenAI: AJUSTES!$C$13
Name EstConservar: PROYECTO!$C$36
Name FmtCalidad: PROYECTO!$C$30
Name FmtEstilo: PROYECTO!$C$31
Name FmtLuz: PROYECTO!$C$32
Name FmtProporcion: PROYECTO!$C$29
Name FotoNombre: PROYECTO!$C$5
Name FotoRuta: PROYECTO!$C$6
Name HistCabecera: HISTORIAL!$B$4
Name L_Bano: LISTAS!$AH$2:$AH$9
Name L_Calidad: LISTAS!$AU$2:$AU$5
Name L_Carpinteria: LISTAS!$Y$2:$Y$9
Name L_Cocina: LISTAS!$AB$2:$AB$10
Name L_Color: LISTAS!$S$2:$S$15
Name L_Encimera: LISTAS!$AE$2:$AE$8
Name L_Estancia: LISTAS!$A$2:$A$19
Name L_Estilo: LISTAS!$G$2:$G$15
Name L_EstiloImagen: LISTAS!$AY$2:$AY$6
Name L_Iluminacion: LISTAS!$AK$2:$AK$8
Name L_Intensidad: LISTAS!$J$2:$J$4
Name L_Luz: LISTAS!$BB$2:$BB$6
Name L_Mobiliario: LISTAS!$AN$2:$AN$6
Name L_ModeloGemini: LISTAS!$BG$2:$BG$3
Name L_ModeloOpenAI: LISTAS!$BI$2:$BI$3
Name L_Motor: LISTAS!$BE$2:$BE$3
Name L_Paredes: LISTAS!$P$2:$P$12
Name L_Proporcion: LISTAS!$AQ$2:$AQ$9
Name L_Suelo: LISTAS!$M$2:$M$14
Name L_Techo: LISTAS!$V$2:$V$8
Name L_Tipo: LISTAS!$D$2:$D$10
Name PromptIA: PROYECTO!$B$44
Name ProyEstancia: PROYECTO!$C$10
Name ProyEstilo: PROYECTO!$C$12
Name ProyIntensidad: PROYECTO!$C$13
Name ProyNombre: PROYECTO!$C$9
Name ProyTipo: PROYECTO!$C$11
Name RefBano: PROYECTO!$C$23
Name RefCarpinteria: PROYECTO!$C$20
Name RefCocina: PROYECTO!$C$21
Name RefColor: PROYECTO!$C$18
Name RefEncimera: PROYECTO!$C$22
Name RefIluminacion: PROYECTO!$C$24
Name RefMobiliario: PROYECTO!$C$25
Name RefNotas: PROYECTO!$C$26
Name RefParedes: PROYECTO!$C$17
Name RefSuelo: PROYECTO!$C$16
Name RefTecho: PROYECTO!$C$19
Name ResArchivo: RESULTADO!$C$26

Sheet INICIO
B1: GAUDÍ
B2: Visualizador de reformas con IA
B4: Sube la foto de un piso o de una estancia, define el formato y las reformas, y obtén una imagen de cómo quedará. La estructura original (paredes, ventanas, puertas, techos y perspectiva) se mantiene siempre.
B6: CÓMO SE USA
B7: 1 | C7: Ve a PROYECTO y carga la foto original (en el móvil la adjuntarás directamente en Gemini o ChatGPT).
B8: 2 | C8: Elige estancia, estilo, reformas y formato en los desplegables de color crema.
B9: 3 | C9: Pulsa GENERAR IMAGEN: verás el ANTES y el DESPUÉS en la hoja RESULTADO.
B11: DOS FORMAS DE GENERAR LA IMAGEN
B12: B | C12: Asistida (esta versión para móvil y tablet): copia el PROMPT de la sección 7 de PROYECTO, abre Gemini o ChatGPT, adjunta la foto y pega el texto. Funciona con una cuenta gratuita.
B13: A | C13: Automática: usa el archivo Gaudi_Reformas.xlsm en Excel de escritorio (lleva macros y conecta con la IA usando tu clave API).
B15: EN EL MÓVIL
B16: 1 | C16: Abre PROYECTO y elige las opciones en los desplegables (toca la celda y luego la flecha).
B17: 2 | C17: Baja a la sección 7, mantén pulsada la celda del PROMPT y elige Copiar.
B18: 3 | C18: Toca «Abrir Gemini» o «Abrir ChatGPT», adjunta tu foto, pega el texto y envía.
B20: IR A…
B21: → PROYECTO · configurar la reforma
B22: → RESULTADO · antes y después
B23: → HISTORIAL · imágenes generadas
B24: → AJUSTES · motor de IA y clave API
B26: LEYENDA
C27: Celda editable (desplegable o texto): solo hay que tocar estas.
C28: Celda calculada o rellenada por la app: no se edita.
C29: Botón de acción (solo en Excel de escritorio con macros).
B31: PRIVACIDAD Y AVISO
B32: La foto y las especificaciones solo se envían al proveedor de IA elegido (Google u OpenAI) cuando generas una imagen. La clave API se guarda en tu equipo, no dentro del archivo. Las imágenes son orientativas: no sustituyen a un proyecto técnico ni a un presupuesto.

Sheet PROYECTO
B1: GAUDÍ · Proyecto de reforma
B2: ← Inicio | C2: Ver RESULTADO →
B3: Rellena de arriba abajo las celdas color crema (toca la celda y elige en la lista).
B4: 1 · FOTO ORIGINAL
B5: Foto | C5: (en el móvil: adjúntala en Gemini)
B6: Ruta del archivo
B8: 2 · PROYECTO Y ESTANCIA
B9: Nombre del proyecto | C9: Ejemplo · Salón calle Mallorca
B10: Estancia | C10: Salón-comedor
B11: Tipo de reforma | C11: Reforma integral
B12: Estilo decorativo | C12: Nórdico
B13: Intensidad del cambio | C13: Media
B15: 3 · REFORMAS POR ELEMENTO
B16: Suelo | C16: Parquet de roble natural
B17: Paredes · acabado | C17: Pintura lisa
B18: Paredes · color | C18: Blanco roto
B19: Techo | C19: Liso blanco
B20: Puertas y ventanas | C20: Puertas lacadas en blanco
B21: Cocina · muebles | C21: Mantener / no aplica
B22: Cocina · encimera | C22: Mantener / no aplica
B23: Baño | C23: Mantener / no aplica
B24: Iluminación | C24: Lámparas colgantes de diseño
B25: Mobiliario y decoración | C25: Amueblar según el estilo
B26: Notas adicionales | C26: Sofá en tonos claros, alfombra de yute y plantas naturales
B28: 4 · FORMATO DE LA IMAGEN
B29: Proporción | C29: Igual que la foto original
B30: Calidad / resolución | C30: Alta (2K)
B31: Estilo de imagen | C31: Foto realista
B32: Luz de la escena | C32: Luz natural de día
B34: 5 · ESTRUCTURA ORIGINAL (SIEMPRE SE CONSERVA)
B35: 🔒 Se mantienen intactos: paredes y tabiques, ventanas, puertas y huecos, techo y altura, vigas, pilares, escaleras, dimensiones y la perspectiva exacta de la foto.
B36: Conservar también
B38: 6 · RESUMEN Y ESTADO
B39: Estado | C39: Versión móvil: usa la sección 7 para generar con Gemini o ChatGPT.
B40: ="Estancia: "&ProyEstancia&" · "&ProyTipo&CHAR(10)&"Estilo: "&ProyEstilo&" (intensidad "&LOWER(ProyIntensidad)&")"&CHAR(10)&"Suelo: "&RefSuelo&" · Paredes: "&RefParedes&" / "&RefColor&CHAR(10)&"Techo: "&RefTecho&" · Carpintería: "&RefCarpinteria&CHAR(10)&IF(AND(CALC!$B$11="-",CALC!$B$12="-"),"","Cocina: "&RefCocina&" · Encimera: "&RefEncimera&CHAR(10))&IF(CALC!$B$13="-","","Baño: "&RefBano&CHAR(10))&"Iluminación: "&RefIluminacion&" · Mobiliario: "&RefMobiliario&CHAR(10)&"Imagen: "&FmtProporcion&" · "&FmtCalidad&" · "&FmtEstilo&" · "&FmtLuz&IF(LEN(TRIM(RefNotas))>0,CHAR(10)&"Notas: "&TRIM(RefNotas),"")&IF(LEN(TRIM(EstConservar))>0,CHAR(10)&"Conservar también: "&TRIM(EstConservar),"") -> Estancia: Salón-comedor · Reforma integral Estilo: Nórdico (intensidad media) Suelo: Parquet de roble natural · Paredes: Pintura lisa / Blanco roto Techo: Liso blanco · Carpintería: Puertas lacadas en blanco Iluminación: Lámparas colgantes de diseño · Mobiliario: Amueblar según el estilo Imagen: Igual que la foto original · Alta (2K) · Foto realista · Luz natural de día Notas: Sofá en tonos claros, alfombra de yute y plantas naturales
B42: 7 · MODO MÓVIL / SIN CLAVE API
B43: 1) Mantén pulsada la celda del PROMPT (abajo) y elige Copiar. 2) Abre Gemini o ChatGPT. 3) Adjunta la foto original, pega el texto y envía. 4) Guarda la imagen que te devuelva.
B44: =CALC!$B$23&" "&CALC!$B$24&" "&CALC!$B$25&" "&CALC!$B$26&IF(CALC!$B$27="",""," "&CALC!$B$27)&" "&CALC!$B$28 -> Interior renovation visualization. Edit the attached photo (space: open living and dining room) to show how it will look after this renovation: complete renovation of all finishes, fixtures, lighting and furniture. STRICT RULE - KEEP THE ORIGINAL ARCHITECTURE: this is the same real space after the renovation. Keep exactly the same camera position, viewpoint, height, angle, lens, perspective, framing and vanishing lines as in the original photo. Do not move, add, remove, resize or reshape any wall, partition, window, door, opening, column, beam, arch, staircase, radiator or built-in element. Keep the room dimensions, ceiling height, layout and proportions identical, so the new image overlays perfectly on the original one. Only surfaces, finishes, colors, fixtures, light fittings and furniture may change, as specified below. Interior design style: Scandinavian: light woods, white and soft neutral tones, cozy textiles, simple functional furniture. Make clearly visible changes while keeping a realistic, coherent result. Changes: floor: natural oak wood plank flooring. Wall finish: smooth painted walls. Wall color: warm off-white. Ceiling: smooth flat white ceiling. Doors and windows: white lacquered interior doors. Light fittings: designer pendant lamps. Furniture and decor: new furniture and decor matching the chosen style, realistically sized for the space. Additional client requests (written in Spanish; follow them as long as they do not change the architecture): Sofá en tonos claros, alfombra de yute y plantas naturales. Output: photorealistic interior photograph, as if taken by a professional real-estate photographer. Lighting: bright natural daylight entering through the existing windows. Keep exactly the same framing and aspect ratio as the original photo. Realistic materials and textures, correct real-world scale, coherent shadows and reflections. No text, labels, watermarks or people.
B45: Abrir Gemini → | C45: Abrir ChatGPT →
B46: El prompt se escribe en inglés porque los modelos de imagen lo siguen con más precisión. Se actualiza solo al cambiar cualquier opción.

Sheet RESULTADO
B1: RESULTADO · ANTES Y DESPUÉS
B2: ← Volver a PROYECTO
B4: ANTES · foto original | I4: DESPUÉS · propuesta de reforma
B5: Inserta aquí la foto original (Insertar › Imagen) | I5: Inserta aquí la imagen generada (Insertar › Imagen)
B24: Fecha
B25: Generado con
B26: Archivo
B27: Reforma
B32: Visualización orientativa generada con inteligencia artificial: puede contener imprecisiones en materiales o mobiliario y no sustituye a un proyecto técnico ni a un presupuesto.

Sheet HISTORIAL
B1: HISTORIAL · imágenes generadas
B2: Se rellena solo cada vez que generas o importas una imagen desde Excel de escritorio. Pulsa el nombre del archivo para abrir la imagen.
B4: Nº | C4: Fecha | D4: Proyecto | E4: Estancia | F4: Tipo de reforma | G4: Estilo | H4: Proporción | I4: Motor IA | J4: Seg. | K4: Resultado | L4: Imagen | M4: Resumen de la reforma

Sheet AJUSTES
B1: AJUSTES · Motor de IA
B2: ← Volver a PROYECTO
B3: Solo para la generación automática en Excel de escritorio. En el móvil no hace falta.
B5: MOTOR DE IA
B6: Motor | C6: Google Gemini (recomendado)
B7: Modelo Gemini | C7: gemini-3.1-flash-image
B8: Modelo OpenAI | C8: gpt-image-1.5
B9: Carpeta de imágenes
B11: CLAVES API · en este equipo, no en el archivo
B12: Clave Gemini | C12: No configurada en este equipo
B13: Clave OpenAI | C13: No configurada en este equipo
B14: Pulsa GUARDAR CLAVE, pega tu clave y después PROBAR CONEXIÓN. Así puedes compartir este Excel sin compartir tu clave.
B16: DÓNDE CONSEGUIR LA CLAVE
B17: Google Gemini | C17: aistudio.google.com/apikey
B18: OpenAI | C18: platform.openai.com/api-keys
B19: El coste por imagen depende del proveedor y del modelo: consulta sus precios. El modo asistido (sección 7 de PROYECTO) usa tu cuenta de Gemini o ChatGPT.
B21: MODELOS DISPONIBLES (octubre 2026)
B22: gemini-3.1-flash-image | C22: Gemini · rápido y de gran calidad. Recomendado.
B23: gemini-3-pro-image-preview | C23: Gemini · máximo detalle; más lento y caro.
B24: gpt-image-1.5 | C24: OpenAI · edición con alta fidelidad a la foto.
B25: gpt-image-2 | C25: OpenAI · última generación.
B26: Si un proveedor retira un modelo, escribe el nombre nuevo en la celda del modelo (se admite cualquier valor).

Sheet LISTAS
A1: Estancia | B1: EN | D1: Tipo de reforma | E1: EN | G1: Estilo | H1: EN | J1: Intensidad | K1: EN | M1: Suelo | N1: EN | P1: Paredes | Q1: EN | S1: Color | T1: EN | V1: Techo | W1: EN | Y1: Carpintería | Z1: EN | AB1: Cocina | AC1: EN | AE1: Encimera | AF1: EN | AH1: Baño | AI1: EN | AK1: Iluminación | AL1: EN | AN1: Mobiliario | AO1: EN | AQ1: Proporción | AR1: Código | AS1: EN | AU1: Calidad | AV1: Gemini imageSize | AW1: OpenAI quality | AY1: Estilo de imagen | AZ1: EN | BB1: Luz | BC1: EN | BE1: Motor IA | BG1: Modelo Gemini | BI1: Modelo OpenAI
A2: Salón | B2: living room | D2: Reforma integral | E2: complete renovation of all finishes, fixtures, lighting and furniture | G2: Nórdico | H2: Scandinavian: light woods, white and soft neutral tones, cozy textiles, simple functional furniture | J2: Sutil | K2: Make subtle, refined changes that stay close to the original look. | M2: Mantener actual | N2: keep the existing floor exactly as it is | P2: Mantener actual | Q2: keep the existing wall finish | S2: Mantener actual | T2: keep the existing colors | V2: Mantener actual | W2: keep the existing ceiling exactly as it is | Y2: Mantener actual | Z2: keep the existing doors and windows unchanged | AB2: Mantener / no aplica | AC2: - | AE2: Mantener / no aplica | AF2: - | AH2: Mantener / no aplica | AI2: - | AK2: Mantener actual | AL2: keep the existing light fittings | AN2: Mantener actual | AO2: keep the existing furniture | AQ2: Igual que la foto original | AR2: auto | AS2: Keep exactly the same framing and aspect ratio as the original photo. | AU2: Borrador rápido | AV2: 1K | AW2: low | AY2: Foto realista | AZ2: photorealistic interior photograph, as if taken by a professional real-estate photographer | BB2: Como en la foto original | BC2: keep the same lighting conditions and light direction as in the original photo | BE2: Google Gemini (recomendado) | BG2: gemini-3.1-flash-image | BI2: gpt-image-1.5
A3: Salón-comedor | B3: open living and dining room | D3: Lavado de cara (pintura y decoración) | E3: cosmetic refresh: new paint, decoration and soft furnishings only | G3: Moderno | H3: modern contemporary: clean lines, neutral palette, sleek finishes | J3: Media | K3: Make clearly visible changes while keeping a realistic, coherent result. | M3: Parquet de roble natural | N3: natural oak wood plank flooring | P3: Pintura lisa | Q3: smooth painted walls | S3: Blanco roto | T3: warm off-white | V3: Liso blanco | W3: smooth flat white ceiling | Y3: Puertas lacadas en blanco | Z3: white lacquered interior doors | AB3: Blanca lacada sin tiradores | AC3: handleless white lacquered cabinets | AE3: Cuarzo blanco | AF3: white quartz | AH3: Baño moderno completo | AI3: fully renovated modern bathroom: walk-in shower, wall-hung vanity, large mirror and large-format tiles, all in the same positions as the existing fixtures | AK3: Focos empotrados | AL3: recessed ceiling spotlights | AN3: Amueblar según el estilo | AO3: new furniture and decor matching the chosen style, realistically sized for the space | AQ3: Horizontal 4:3 | AR3: 4:3 | AS3: Final image aspect ratio 4:3: adapt the framing only by extending or cropping at the edges, never altering the existing architecture. | AU3: Estándar (1K) | AV3: 1K | AW3: medium | AY3: Render 3D arquitectónico | AZ3: high-end photorealistic architectural 3D render | BB3: Luz natural de día | BC3: bright natural daylight entering through the existing windows | BE3: OpenAI (GPT Image) | BG3: gemini-3-pro-image-preview | BI3: gpt-image-2
A4: Comedor | B4: dining room | D4: Home staging (vender / alquilar) | E4: home staging to sell or rent: clean, bright, neutral and inviting | G4: Minimalista | H4: minimalist: uncluttered, essential furniture, hidden storage, calm monochrome palette | J4: Transformación total | K4: Make a complete transformation of finishes, colors and furniture (but never of the architecture). | M4: Parquet en espiga | N4: herringbone oak parquet | P4: Papel pintado | Q4: elegant wallpaper | S4: Blanco puro | T4: pure white | V4: Foseado con LED indirecto | W4: perimeter ceiling cove with indirect LED light (ceiling height unchanged) | Y4: Puertas de roble | Z4: natural oak interior doors | AB4: Madera natural | AC4: natural wood cabinets | AE4: Porcelánico efecto mármol | AF4: marble-effect porcelain | AH4: Plato de ducha + mampara | AI4: walk-in shower with flush tray and glass screen in the place of the existing bath or shower | AK4: Tiras LED indirectas | AL4: indirect LED strip lighting | AN4: Home staging ligero | AO4: light home staging: a few well-chosen furniture pieces, plants and decor | AQ4: Horizontal 3:2 | AR4: 3:2 | AS4: Final image aspect ratio 3:2: adapt the framing only by extending or cropping at the edges, never altering the existing architecture. | AU4: Alta (2K) | AV4: 2K | AW4: high | AY4: Revista de decoración | AZ4: polished, carefully styled interior-design magazine photograph | BB4: Atardecer cálido | BC4: warm golden-hour sunlight through the existing windows
A5: Cocina | B5: kitchen | D5: Reforma de cocina | E5: kitchen renovation | G5: Industrial | H5: industrial: black metal, raw wood, concrete textures, exposed materials | M5: Tarima vinílica efecto madera | N5: wood-effect vinyl plank flooring | P5: Microcemento | Q5: microcement wall finish | S5: Gris perla | T5: pearl grey | V5: Vigas de madera vistas (si existen) | W5: the existing ceiling beams exposed and finished in natural wood | Y5: Puertas negras modernas | Z5: modern black interior doors | AB5: Verde salvia | AC5: sage green cabinets | AE5: Madera maciza | AF5: solid wood | AH5: Bañera exenta | AI5: freestanding bathtub in the place of the existing bath | AK5: Lámparas colgantes de diseño | AL5: designer pendant lamps | AN5: Renovar textiles y decoración | AO5: same furniture layout with updated textiles, cushions, rugs, curtains and decor | AQ5: Horizontal 16:9 | AR5: 16:9 | AS5: Final image aspect ratio 16:9: adapt the framing only by extending or cropping at the edges, never altering the existing architecture. | AU5: Máxima (4K, más lenta) | AV5: 4K | AW5: high | AY5: Boceto a mano | AZ5: hand-drawn architectural sketch with ink lines and a soft watercolor wash, same perspective | BB5: Día nublado, luz suave | BC5: soft, diffuse overcast daylight
A6: Cocina abierta al salón | B6: open-plan kitchen connected to the living room | D6: Reforma de baño | E6: bathroom renovation | G6: Mediterráneo | H6: Mediterranean: whitewashed walls, natural fibers, terracotta, warm wood and touches of blue | M6: Porcelánico gran formato gris | N6: large-format light grey porcelain tiles | P6: Revestimiento de madera | Q6: wood panel wall cladding | S6: Greige | T6: greige (warm grey-beige) | V6: Bóveda catalana restaurada (si existe) | W6: the existing Catalan vault ceiling restored with exposed brick | Y6: Ventanas de aluminio negro | Z6: black aluminium window frames | AB6: Gris antracita mate | AC6: matte anthracite grey cabinets | AE6: Granito negro | AF6: black granite | AH6: Mueble suspendido de madera | AI6: wall-hung wooden vanity with modern washbasin | AK6: Lámparas de pie y sobremesa | AL6: floor and table lamps for warm ambient light | AN6: Vaciar (sin muebles) | AO6: remove all furniture and objects, leaving the room empty and clean | AQ6: Cuadrada 1:1 | AR6: 1:1 | AS6: Final image aspect ratio 1:1: adapt the framing only by extending or cropping at the edges, never altering the existing architecture. | AY6: Acuarela | AZ6: soft architectural watercolor illustration, same perspective | BB6: Noche con luces encendidas | BC6: evening ambience with the warm artificial lights switched on
A7: Baño | B7: bathroom | D7: Cambio de suelos | E7: new flooring | G7: Japandi | H7: Japandi: natural wood, earthy muted tones, low furniture, serene atmosphere | M7: Porcelánico efecto mármol | N7: large-format marble-effect porcelain tiles | P7: Ladrillo visto | Q7: exposed brick | S7: Beige arena | T7: sand beige | V7: Molduras clásicas | W7: classic plaster cornices and ceiling moldings | Y7: Ventanas de PVC blanco | Z7: white PVC window frames | AB7: Azul marino | AC7: navy blue cabinets | AE7: Microcemento | AF7: microcement | AH7: Mueble suspendido blanco | AI7: wall-hung white vanity with modern washbasin | AK7: Carril con focos | AL7: ceiling track with spotlights | AQ7: Vertical 4:5 (Instagram) | AR7: 4:5 | AS7: Final image aspect ratio 4:5: adapt the framing only by extending or cropping at the edges, never altering the existing architecture.
A8: Aseo | B8: small guest toilet | D8: Amueblar piso vacío | E8: furnishing of the empty space | G8: Rústico moderno | H8: modern rustic: natural wood, stone and warm textures with modern comfort | M8: Porcelánico efecto madera | N8: wood-effect porcelain tiles | P8: Azulejo / porcelánico | Q8: wall tiles | S8: Verde salvia | T8: sage green | V8: Listones de madera | W8: wooden slat ceiling cladding | Y8: Ventanas de madera | Z8: wooden window frames | AB8: Bicolor madera + blanco | AC8: two-tone cabinets: wood lower units and white upper units | AE8: Acero inoxidable | AF8: stainless steel | AH8: Grifería negra mate | AI8: matte black taps and fittings | AK8: Apliques de pared | AL8: wall sconces | AQ8: Vertical 3:4 | AR8: 3:4 | AS8: Final image aspect ratio 3:4: adapt the framing only by extending or cropping at the edges, never altering the existing architecture.
A9: Dormitorio principal | B9: master bedroom | D9: Vaciar estancia | E9: removal of all furniture and clutter, leaving the space empty and clean | G9: Clásico elegante | H9: classic elegant: moldings, refined furniture, symmetry and soft neutral colors | M9: Microcemento | N9: seamless microcement floor in a soft neutral tone | P9: Zócalo de azulejo + pintura | Q9: tiled wainscot with painted wall above | S9: Azul nórdico | T9: soft Nordic blue | Y9: Puertas y ventanas nuevas a juego | Z9: new doors and window frames matching the chosen style | AB9: Negra mate | AC9: matte black cabinets | AH9: Grifería dorada | AI9: brushed brass taps and fittings | AQ9: Vertical 9:16 (stories) | AR9: 9:16 | AS9: Final image aspect ratio 9:16: adapt the framing only by extending or cropping at the edges, never altering the existing architecture.
A10: Dormitorio | B10: bedroom | D10: Rehabilitación de época | E10: respectful restoration that recovers the original period features | G10: Lujo contemporáneo | H10: contemporary luxury: marble, brass details, designer lighting, rich textures | M10: Baldosa hidráulica | N10: traditional patterned hydraulic cement tiles | P10: Molduras (boiserie) | Q10: classic wall moldings (boiserie) | S10: Azul marino | T10: navy blue | AB10: Rústica con cuarterones | AC10: rustic framed shaker-style cabinets
A11: Dormitorio infantil | B11: children's bedroom | G11: Boho | H11: bohemian: rattan, natural fibers, plants, warm earthy colors, layered textiles | M11: Terrazo | N11: terrazzo floor | P11: Estuco / cal | Q11: lime plaster or Venetian stucco finish | S11: Terracota | T11: terracotta
A12: Despacho / estudio | B12: home office | G12: Mid-century | H12: mid-century modern: walnut wood, tapered legs, organic shapes, retro accent colors | M12: Barro cocido | N12: handmade terracotta tiles | P12: Piedra natural | Q12: natural stone cladding | S12: Tonos tierra | T12: earthy tones
A13: Recibidor | B13: entrance hall | G13: Modernista (Gaudí) | H13: Catalan Modernisme inspired by Antoni Gaudi: organic curves, hydraulic mosaic tiles, trencadis accents, stained glass, wrought iron and natural motifs | M13: Moqueta | N13: wall-to-wall carpet in a neutral tone | S13: Rosa empolvado | T13: dusty pink
A14: Pasillo | B14: hallway | G14: Costero | H14: coastal: airy whites, sand and soft blue tones, natural linen, light woods | M14: Restaurar el suelo actual | N14: the existing floor restored and polished, keeping its original pattern | S14: Gris antracita | T14: anthracite grey
A15: Terraza / balcón | B15: terrace or balcony | G15: Neutro para vender | H15: neutral, bright and universally appealing, ideal for a property listing | S15: Negro | T15: black
A16: Galería / lavadero | B16: utility and laundry room
A17: Buhardilla / ático | B17: attic room under a sloped roof
A18: Local comercial | B18: commercial premises
A19: Piso completo (vista general) | B19: apartment

Sheet CALC
A1: Clave | B1: Valor (fórmula) | C1: Descripción
A2: EN_Estancia | B2: =IFERROR(VLOOKUP(ProyEstancia,T_Estancia,2,FALSE),"room") -> open living and dining room | C2: Estancia en inglés
A3: EN_Tipo | B3: =IFERROR(VLOOKUP(ProyTipo,T_Tipo,2,FALSE),"renovation") -> complete renovation of all finishes, fixtures, lighting and furniture | C3: Tipo de reforma
A4: EN_Estilo | B4: =IFERROR(VLOOKUP(ProyEstilo,T_Estilo,2,FALSE),"modern") -> Scandinavian: light woods, white and soft neutral tones, cozy textiles, simple functional furniture | C4: Estilo decorativo
A5: EN_Intensidad | B5: =IFERROR(VLOOKUP(ProyIntensidad,T_Intensidad,2,FALSE),"") -> Make clearly visible changes while keeping a realistic, coherent result. | C5: Intensidad
A6: EN_Suelo | B6: =IFERROR(VLOOKUP(RefSuelo,T_Suelo,2,FALSE),"keep the existing floor") -> natural oak wood plank flooring | C6: Suelo
A7: EN_Paredes | B7: =IFERROR(VLOOKUP(RefParedes,T_Paredes,2,FALSE),"keep the existing wall finish") -> smooth painted walls | C7: Acabado de paredes
A8: EN_Color | B8: =IFERROR(VLOOKUP(RefColor,T_Color,2,FALSE),"keep the existing colors") -> warm off-white | C8: Color
A9: EN_Techo | B9: =IFERROR(VLOOKUP(RefTecho,T_Techo,2,FALSE),"keep the existing ceiling") -> smooth flat white ceiling | C9: Techo
A10: EN_Carpinteria | B10: =IFERROR(VLOOKUP(RefCarpinteria,T_Carpinteria,2,FALSE),"keep the existing doors and windows") -> white lacquered interior doors | C10: Puertas y ventanas
A11: EN_Cocina | B11: =IFERROR(VLOOKUP(RefCocina,T_Cocina,2,FALSE),"-") -> - | C11: Cocina ('-' = no se menciona)
A12: EN_Encimera | B12: =IFERROR(VLOOKUP(RefEncimera,T_Encimera,2,FALSE),"-") -> - | C12: Encimera
A13: EN_Bano | B13: =IFERROR(VLOOKUP(RefBano,T_Bano,2,FALSE),"-") -> - | C13: Baño
A14: EN_Iluminacion | B14: =IFERROR(VLOOKUP(RefIluminacion,T_Iluminacion,2,FALSE),"keep the existing light fittings") -> designer pendant lamps | C14: Lámparas
A15: EN_Mobiliario | B15: =IFERROR(VLOOKUP(RefMobiliario,T_Mobiliario,2,FALSE),"keep the existing furniture") -> new furniture and decor matching the chosen style, realistically sized for the space | C15: Mobiliario
A16: EN_FmtEstilo | B16: =IFERROR(VLOOKUP(FmtEstilo,T_EstiloImagen,2,FALSE),"photorealistic interior photograph") -> photorealistic interior photograph, as if taken by a professional real-estate photographer | C16: Estilo de imagen
A17: EN_FmtLuz | B17: =IFERROR(VLOOKUP(FmtLuz,T_Luz,2,FALSE),"keep the original lighting") -> bright natural daylight entering through the existing windows | C17: Luz
A18: CodProporcion | B18: =IFERROR(VLOOKUP(FmtProporcion,T_Proporcion,2,FALSE),"auto") -> auto | C18: Proporción para la API (auto = la de la foto)
A19: EN_Proporcion | B19: =IFERROR(VLOOKUP(FmtProporcion,T_Proporcion,3,FALSE),"") -> Keep exactly the same framing and aspect ratio as the original photo. | C19: Texto de proporción
A20: CodResolucion | B20: =IFERROR(VLOOKUP(FmtCalidad,T_Calidad,2,FALSE),"1K") -> 2K | C20: imageSize de Gemini
A21: CodCalidadOpenAI | B21: =IFERROR(VLOOKUP(FmtCalidad,T_Calidad,3,FALSE),"medium") -> high | C21: quality de OpenAI
A23: P_Intro | B23: ="Interior renovation visualization. Edit the attached photo (space: "&CALC!$B$2&") to show how it will look after this renovation: "&CALC!$B$3&"." -> Interior renovation visualization. Edit the attached photo (space: open living and dining room) to show how it will look after this renovation: complete renovation of all finishes, fixtures, lighting and furniture. | C23: Introducción
A24: P_Estructura | B24: ="STRICT RULE - KEEP THE ORIGINAL ARCHITECTURE: this is the same real space after the renovation. Keep exactly the same camera position, viewpoint, height, angle, lens, perspective, framing and vanishing lines as in the original photo. Do not move, add, remove, resize or reshape any wall, partition, window, door, opening, column, beam, arch, staircase, radiator or built-in element. Keep the room dimensions, ceiling height, layout and proportions identical, so the new image overlays perfectly on the original one. Only surfaces, finishes, colors, fixtures, light fittings and furniture may change, as specified below."&IF(LEN(TRIM(EstConservar))>0," Also keep exactly as they are: "&TRIM(EstConservar)&".","") -> STRICT RULE - KEEP THE ORIGINAL ARCHITECTURE: this is the same real space after the renovation. Keep exactly the same camera position, viewpoint, height, angle, lens, perspective, framing and vanishing lines as in the original photo. Do not move, add, remove, resize or reshape any wall, partition, window, door, opening, column, beam, arch, staircase, radiator or built-in element. Keep the room dimensions, ceiling height, layout and proportions identical, so the new image overlays perfectly on the original one. Only surfaces, finishes, colors, fixtures, light fittings and furniture may change, as specified below. | C24: Bloqueo de estructura (siempre presente)
A25: P_Estilo | B25: ="Interior design style: "&CALC!$B$4&". "&CALC!$B$5 -> Interior design style: Scandinavian: light woods, white and soft neutral tones, cozy textiles, simple functional furniture. Make clearly visible changes while keeping a realistic, coherent result. | C25: Estilo e intensidad
A26: P_Cambios | B26: ="Changes: floor: "&CALC!$B$6&". Wall finish: "&CALC!$B$7&". Wall color: "&CALC!$B$8&". Ceiling: "&CALC!$B$9&". Doors and windows: "&CALC!$B$10&"."&IF(CALC!$B$11="-",""," Kitchen cabinets: "&CALC!$B$11&".")&IF(CALC!$B$12="-",""," Countertop: "&CALC!$B$12&".")&IF(CALC!$B$13="-",""," Bathroom: "&CALC!$B$13&".")&" Light fittings: "&CALC!$B$14&". Furniture and decor: "&CALC!$B$15&"." -> Changes: floor: natural oak wood plank flooring. Wall finish: smooth painted walls. Wall color: warm off-white. Ceiling: smooth flat white ceiling. Doors and windows: white lacquered interior doors. Light fittings: designer pendant lamps. Furniture and decor: new furniture and decor matching the chosen style, realistically sized for the space. | C26: Cambios por elemento
A27: P_Notas | B27: =IF(LEN(TRIM(RefNotas))>0,"Additional client requests (written in Spanish; follow them as long as they do not change the architecture): "&TRIM(RefNotas)&".","") -> Additional client requests (written in Spanish; follow them as long as they do not change the architecture): Sofá en tonos claros, alfombra de yute y plantas naturales. | C27: Notas del usuario
A28: P_Salida | B28: ="Output: "&CALC!$B$16&". Lighting: "&CALC!$B$17&". "&CALC!$B$19&" Realistic materials and textures, correct real-world scale, coherent shadows and reflections. No text, labels, watermarks or people." -> Output: photorealistic interior photograph, as if taken by a professional real-estate photographer. Lighting: bright natural daylight entering through the existing windows. Keep exactly the same framing and aspect ratio as the original photo. Realistic materials and textures, correct real-world scale, coherent shadows and reflections. No text, labels, watermarks or people. | C28: Formato de salida
